CHANGELOG.rst
LICENSE.rst
MANIFEST.in
README.rst
obsub.py
setup.cfg
setup.py
obsub.egg-info/PKG-INFO
obsub.egg-info/SOURCES.txt
obsub.egg-info/dependency_links.txt
obsub.egg-info/top_level.txt
test/test_core.py
test/test_signature.py
test/test_weakref.py
test/py3/test_signature.py