Metadata-Version: 1.1
Name: obsub
Version: 0.2
Summary: Implementation of the observer pattern via a decorator
Home-page: https://github.com/aepsil0n/obsub
Author: Eduard Bopp
Author-email: eduard.bopp@aepsil0n.de
License: Public Domain
Platform: UNKNOWN
Classifier: Development Status :: 4 - Beta
Classifier: Intended Audience :: Developers
Classifier: License :: CC0 1.0 Universal (CC0 1.0) Public Domain Dedication
Classifier: Operating System :: OS Independent
Classifier: Programming Language :: Python
Classifier: Topic :: Software Development
